gmx/__init__.py
gmx/extensions.py
gmx/main.py
gmx/cmd/__init__.py
gmx/cmd/initialize.py
gmx/cmd/project.py
gmx/cmd/runner.py
gmx/cmd/workflow.py
gmx/extension_logic/__init__.py
gmx/extension_logic/converter.py
gmx/extensions_logic/__init__.py
gmx/extensions_logic/converter.py
gmx/logic/__init__.py
gmx/logic/common.py
gmx/logic/fileops.py
gmx/logic/generation.py
gmx/logic/initialize.py
gmx/logic/preference.py
gmx/logic/project.py
gmx/logic/runner.py
gmx/logic/workflow.py
genmax-0.1.9.dist-info/LICENSE
genmax-0.1.9.dist-info/METADATA
genmax-0.1.9.dist-info/WHEEL
genmax-0.1.9.dist-info/entry_points.txt
genmax-0.1.9.dist-info/top_level.txt
genmax-0.1.9.dist-info/RECORD
