Metadata-Version: 2.1
Name: genmax
Version: 0.1.9
Summary: A simple code generation tool.
Home-page: https://https://github.com/razaibi/genmax/
Author: Raza Balbale
License: Apache 2.0
Project-URL: Documentation, https://github.com/razaibi/genmax/README.md
Project-URL: Source, https://github.com/razaibi/genmax
Project-URL: Tracker, https://github.com/razaibi/genmax/
Keywords: cli code generator automation
License-File: LICENSE
Requires-Dist: PyYAML==6.0
Requires-Dist: Jinja2==3.1.2
Requires-Dist: pluralizer==1.2.0
Requires-Dist: case-switcher==1.3.13
Requires-Dist: typer==0.9.0
